speedbump/__init__.py
speedbump/_version.py
speedbump/cli.py
speedbump-0.1.2.dist-info/METADATA
speedbump-0.1.2.dist-info/WHEEL
speedbump-0.1.2.dist-info/entry_points.txt
speedbump-0.1.2.dist-info/top_level.txt
speedbump-0.1.2.dist-info/RECORD
